{
    "databases": {
        "consul_db": {
            "import_path": "ConsulDB",
            "config": {
                "hosts": ["127.0.0.1"],
                "port": 8500,
                "login": "",
                "password": ""
            }
        }
    },
    "models": [
        {
            "import_path": "cortx.utils.ha.dm.models.decisiondb.DecisionModel",
            "database": "consul_db",
            "config": {
                "consul_db": {
                    "collection": "HA"
                }
            }
        }
    ]
}
